Workbook

Sheet Control
A1: SaaS Revenue Intelligence | MRR, Retention & Billing Controls
A2: Synthetic data from a seeded generator. Not real company, customer or financial results.
A3: Built by src/excel/build_workbook.py from the tested dbt marts. No macros. Shaded cells on Scenario Inputs are the only editable cells.
A4: Control item | B4: Value
A5: Refreshed (UTC) | B5: 2026-09-19 20:07
A6: Source commit | B6: a13e601c1309
A7: Run ID (hash of exports) | B7: 73d30c5e8e7b
A8: Data window | B8: 2023-01 to 2025-12
A9: MRR bridge breaks | B9: =COUNTIF('MRR Bridge'!L5:L40,"CHECK")
A10: Opening balance breaks | B10: =COUNTIF('MRR Bridge'!P5:P40,"CHECK")
A11: Billing reconciliation breaks | B11: =COUNTIF('Billing Reconciliation'!N5:N40,"CHECK")
A12: Reconciliation status | B12: =IF(B9+B10+B11=0,"ALL CHECKS PASS","REVIEW")
A13: Latest closing MRR | B13: ='MRR Bridge'!H40
A14: Latest net revenue retention | B14: ='MRR Bridge'!M40
A15: Latest gross revenue retention | B15: ='MRR Bridge'!N40
A16: Total invoiced | B16: ='Billing Reconciliation'!C41
A17: Total failed-payment exposure | B17: ='Billing Reconciliation'!E41
A18: Finance exceptions queued | B18: =COUNTA(Exceptions!A9:A977)
A19: Caveat | B19: December 2025 churn is concentrated on the last day of the data window; treat it as a data-dating question.
A21: Export | B21: SHA-256
A22: billing_reconciliation.csv | B22: b99fa456d402cfbd91681ea16f34492af00e56e7377982ecb9d8577c27910af9
A23: finance_exceptions.csv | B23: f815681b348f2f610ec8e3a4727bf41513270a777b2170681c533396ff1c989a
A24: mrr_bridge.csv | B24: 79ef29980cd4631517e4f25d320373237fdc115902e2802c4d65758e252e2cd8

Sheet MRR Bridge
A1: MRR bridge and roll-forward checks
A2: Columns B to H are warehouse values. Columns I to P are formulas.
A4: Month | B4: Opening | C4: New | D4: Expansion | E4: Reactivation | F4: Contraction | G4: Churned | H4: Closing (warehouse) | I4: Net new | J4: Closing (calculated) | K4: Variance | L4: Bridge check | M4: NRR | N4: GRR | O4: ARR | P4: Opening ties to prior close
A5: 44927 | B5: 0 | C5: 54743.25 | D5: 0 | E5: 0 | F5: 0 | G5: 0 | H5: 54743.25 | I5: =C5+D5+E5-F5-G5 | J5: =B5+I5 | K5: =ROUND(J5-H5,2) | L5: =IF(ABS(K5)<=0.01,"OK","CHECK") | M5: =IF(B5>0,(B5+D5+E5-F5-G5)/B5,"") | N5: =IF(B5>0,(B5-F5-G5)/B5,"") | O5: =H5*12 | P5: ="OK"
A6: 44958 | B6: 54743.25 | C6: 118635.15 | D6: 0 | E6: 0 | F6: 0 | G6: 0 | H6: 173378.4 | I6: =C6+D6+E6-F6-G6 | J6: =B6+I6 | K6: =ROUND(J6-H6,2) | L6: =IF(ABS(K6)<=0.01,"OK","CHECK") | M6: =IF(B6>0,(B6+D6+E6-F6-G6)/B6,"") | N6: =IF(B6>0,(B6-F6-G6)/B6,"") | O6: =H6*12 | P6: =IF(ABS(B6-H5)<=0.01,"OK","CHECK")
A7: 44986 | B7: 173378.4 | C7: 47009.6 | D7: 3095.61 | E7: 0 | F7: 6816.75 | G7: 0 | H7: 216666.86 | I7: =C7+D7+E7-F7-G7 | J7: =B7+I7 | K7: =ROUND(J7-H7,2) | L7: =IF(ABS(K7)<=0.01,"OK","CHECK") | M7: =IF(B7>0,(B7+D7+E7-F7-G7)/B7,"") | N7: =IF(B7>0,(B7-F7-G7)/B7,"") | O7: =H7*12 | P7: =IF(ABS(B7-H6)<=0.01,"OK","CHECK")
A8: 45017 | B8: 216666.86 | C8: 50077.45 | D8: 411.12 | E8: 0 | F8: 395 | G8: 0 | H8: 266760.43 | I8: =C8+D8+E8-F8-G8 | J8: =B8+I8 | K8: =ROUND(J8-H8,2) | L8: =IF(ABS(K8)<=0.01,"OK","CHECK") | M8: =IF(B8>0,(B8+D8+E8-F8-G8)/B8,"") | N8: =IF(B8>0,(B8-F8-G8)/B8,"") | O8: =H8*12 | P8: =IF(ABS(B8-H7)<=0.01,"OK","CHECK")
A9: 45047 | B9: 266760.43 | C9: 72664.85 | D9: 3078.61 | E9: 0 | F9: 419.69 | G9: 0 | H9: 342084.2 | I9: =C9+D9+E9-F9-G9 | J9: =B9+I9 | K9: =ROUND(J9-H9,2) | L9: =IF(ABS(K9)<=0.01,"OK","CHECK") | M9: =IF(B9>0,(B9+D9+E9-F9-G9)/B9,"") | N9: =IF(B9>0,(B9-F9-G9)/B9,"") | O9: =H9*12 | P9: =IF(ABS(B9-H8)<=0.01,"OK","CHECK")
A10: 45078 | B10: 342084.2 | C10: 27209.25 | D10: 2553.51 | E10: 0 | F10: 3006.3 | G10: 0 | H10: 368840.66 | I10: =C10+D10+E10-F10-G10 | J10: =B10+I10 | K10: =ROUND(J10-H10,2) | L10: =IF(ABS(K10)<=0.01,"OK","CHECK") | M10: =IF(B10>0,(B10+D10+E10-F10-G10)/B10,"") | N10: =IF(B10>0,(B10-F10-G10)/B10,"") | O10: =H10*12 | P10: =IF(ABS(B10-H9)<=0.01,"OK","CHECK")
A11: 45108 | B11: 368840.66 | C11: 52774.5 | D11: 2057.82 | E11: 0 | F11: 140.4 | G11: 0 | H11: 423532.58 | I11: =C11+D11+E11-F11-G11 | J11: =B11+I11 | K11: =ROUND(J11-H11,2) | L11: =IF(ABS(K11)<=0.01,"OK","CHECK") | M11: =IF(B11>0,(B11+D11+E11-F11-G11)/B11,"") | N11: =IF(B11>0,(B11-F11-G11)/B11,"") | O11: =H11*12 | P11: =IF(ABS(B11-H10)<=0.01,"OK","CHECK")
A12: 45139 | B12: 423532.58 | C12: 56215.35 | D12: 5783.11 | E12: 0 | F12: 429.35 | G12: 0 | H12: 485101.69 | I12: =C12+D12+E12-F12-G12 | J12: =B12+I12 | K12: =ROUND(J12-H12,2) | L12: =IF(ABS(K12)<=0.01,"OK","CHECK") | M12: =IF(B12>0,(B12+D12+E12-F12-G12)/B12,"") | N12: =IF(B12>0,(B12-F12-G12)/B12,"") | O12: =H12*12 | P12: =IF(ABS(B12-H11)<=0.01,"OK","CHECK")
A13: 45170 | B13: 485101.69 | C13: 35537.1 | D13: 7827.86 | E13: 0 | F13: 1142.74 | G13: 0 | H13: 527323.91 | I13: =C13+D13+E13-F13-G13 | J13: =B13+I13 | K13: =ROUND(J13-H13,2) | L13: =IF(ABS(K13)<=0.01,"OK","CHECK") | M13: =IF(B13>0,(B13+D13+E13-F13-G13)/B13,"") | N13: =IF(B13>0,(B13-F13-G13)/B13,"") | O13: =H13*12 | P13: =IF(ABS(B13-H12)<=0.01,"OK","CHECK")
A14: 45200 | B14: 527323.91 | C14: 47480.75 | D14: 1951.58 | E14: 0 | F14: 1425.56 | G14: 9650.25 | H14: 565680.43 | I14: =C14+D14+E14-F14-G14 | J14: =B14+I14 | K14: =ROUND(J14-H14,2) | L14: =IF(ABS(K14)<=0.01,"OK","CHECK") | M14: =IF(B14>0,(B14+D14+E14-F14-G14)/B14,"") | N14: =IF(B14>0,(B14-F14-G14)/B14,"") | O14: =H14*12 | P14: =IF(ABS(B14-H13)<=0.01,"OK","CHECK")
A15: 45231 | B15: 565680.43 | C15: 30726.1 | D15: 6587.46 | E15: 0 | F15: 543.2 | G15: 1317.05 | H15: 601133.74 | I15: =C15+D15+E15-F15-G15 | J15: =B15+I15 | K15: =ROUND(J15-H15,2) | L15: =IF(ABS(K15)<=0.01,"OK","CHECK") | M15: =IF(B15>0,(B15+D15+E15-F15-G15)/B15,"") | N15: =IF(B15>0,(B15-F15-G15)/B15,"") | O15: =H15*12 | P15: =IF(ABS(B15-H14)<=0.01,"OK","CHECK")
A16: 45261 | B16: 601133.74 | C16: 31257.35 | D16: 2411.9 | E16: 0 | F16: 6253.41 | G16: 1069.46 | H16: 627480.12 | I16: =C16+D16+E16-F16-G16 | J16: =B16+I16 | K16: =ROUND(J16-H16,2) | L16: =IF(ABS(K16)<=0.01,"OK","CHECK") | M16: =IF(B16>0,(B16+D16+E16-F16-G16)/B16,"") | N16: =IF(B16>0,(B16-F16-G16)/B16,"") | O16: =H16*12 | P16: =IF(ABS(B16-H15)<=0.01,"OK","CHECK")
A17: 45292 | B17: 627480.12 | C17: 93401.1 | D17: 8787.75 | E17: 0 | F17: 1363.3 | G17: 312 | H17: 727993.67 | I17: =C17+D17+E17-F17-G17 | J17: =B17+I17 | K17: =ROUND(J17-H17,2) | L17: =IF(ABS(K17)<=0.01,"OK","CHECK") | M17: =IF(B17>0,(B17+D17+E17-F17-G17)/B17,"") | N17: =IF(B17>0,(B17-F17-G17)/B17,"") | O17: =H17*12 | P17: =IF(ABS(B17-H16)<=0.01,"OK","CHECK")
... A40: 45992 | B40: 2174316.6 | C40: 61123.55 | D40: 17342.09 | E40: 0 | F40: 2929.51 | G40: 335100.15 | H40: 1914752.6 | I40: =C40+D40+E40-F40-G40 | J40: =B40+I40 | K40: =ROUND(J40-H40,2) | L40: =IF(ABS(K40)<=0.01,"OK","CHECK") | M40: =IF(B40>0,(B40+D40+E40-F40-G40)/B40,"") | N40: =IF(B40>0,(B40-F40-G40)/B40,"") | O40: =H40*12 | P40: =IF(ABS(B40-H39)<=0.01,"OK","CHECK")

Sheet Billing Reconciliation
A1: Invoice, payment, refund and revenue tie-out
A2: Invoices must equal successful payments plus unpaid exposure. Recognized plus deferred must equal invoiced.
A4: Invoice month | B4: Invoices | C4: Invoiced | D4: Paid | E4: Unpaid (failed) | F4: Refunded | G4: Net cash (warehouse) | H4: Recognized | I4: Deferred | J4: Tie-out variance | K4: Net cash (calculated) | L4: Cash variance | M4: Revenue variance | N4: Reconciliation check
A5: 44927 | B5: 17 | C5: 54743.25 | D5: 54743.25 | E5: 0 | F5: 337.73 | G5: 54405.52 | H5: 54743.25 | I5: 0 | J5: =ROUND(C5-D5-E5,2) | K5: =D5-F5 | L5: =ROUND(K5-G5,2) | M5: =ROUND(C5-H5-I5,2) | N5: =IF(AND(ABS(J5)<=0.01,ABS(L5)<=0.01,ABS(M5)<=0.01),"OK","CHECK")
A6: 44958 | B6: 55 | C6: 173378.4 | D6: 140669.25 | E6: 32709.15 | F6: 2346.75 | G6: 138322.5 | H6: 173378.4 | I6: 0 | J6: =ROUND(C6-D6-E6,2) | K6: =D6-F6 | L6: =ROUND(K6-G6,2) | M6: =ROUND(C6-H6-I6,2) | N6: =IF(AND(ABS(J6)<=0.01,ABS(L6)<=0.01,ABS(M6)<=0.01),"OK","CHECK")
A7: 44986 | B7: 83 | C7: 216666.86 | D7: 216198.86 | E7: 468 | F7: 515.48 | G7: 215683.38 | H7: 216666.86 | I7: 0 | J7: =ROUND(C7-D7-E7,2) | K7: =D7-F7 | L7: =ROUND(K7-G7,2) | M7: =ROUND(C7-H7-I7,2) | N7: =IF(AND(ABS(J7)<=0.01,ABS(L7)<=0.01,ABS(M7)<=0.01),"OK","CHECK")
A8: 45017 | B8: 113 | C8: 266760.43 | D8: 261490.38 | E8: 5270.05 | F8: 268.6 | G8: 261221.78 | H8: 266760.43 | I8: 0 | J8: =ROUND(C8-D8-E8,2) | K8: =D8-F8 | L8: =ROUND(K8-G8,2) | M8: =ROUND(C8-H8-I8,2) | N8: =IF(AND(ABS(J8)<=0.01,ABS(L8)<=0.01,ABS(M8)<=0.01),"OK","CHECK")
A9: 45047 | B9: 141 | C9: 342084.2 | D9: 323272.84 | E9: 18811.36 | F9: 2808.9 | G9: 320463.94 | H9: 342084.2 | I9: 0 | J9: =ROUND(C9-D9-E9,2) | K9: =D9-F9 | L9: =ROUND(K9-G9,2) | M9: =ROUND(C9-H9-I9,2) | N9: =IF(AND(ABS(J9)<=0.01,ABS(L9)<=0.01,ABS(M9)<=0.01),"OK","CHECK")
A10: 45078 | B10: 160 | C10: 368840.66 | D10: 345319.41 | E10: 23521.25 | F10: 340.13 | G10: 344979.28 | H10: 368840.66 | I10: 0 | J10: =ROUND(C10-D10-E10,2) | K10: =D10-F10 | L10: =ROUND(K10-G10,2) | M10: =ROUND(C10-H10-I10,2) | N10: =IF(AND(ABS(J10)<=0.01,ABS(L10)<=0.01,ABS(M10)<=0.01),"OK","CHECK")
A11: 45108 | B11: 191 | C11: 423532.58 | D11: 404785.47 | E11: 18747.11 | F11: 5248.42 | G11: 399537.05 | H11: 423532.58 | I11: 0 | J11: =ROUND(C11-D11-E11,2) | K11: =D11-F11 | L11: =ROUND(K11-G11,2) | M11: =ROUND(C11-H11-I11,2) | N11: =IF(AND(ABS(J11)<=0.01,ABS(L11)<=0.01,ABS(M11)<=0.01),"OK","CHECK")
A12: 45139 | B12: 220 | C12: 485101.69 | D12: 459542.12 | E12: 25559.57 | F12: 58.5 | G12: 459483.62 | H12: 485101.69 | I12: 0 | J12: =ROUND(C12-D12-E12,2) | K12: =D12-F12 | L12: =ROUND(K12-G12,2) | M12: =ROUND(C12-H12-I12,2) | N12: =IF(AND(ABS(J12)<=0.01,ABS(L12)<=0.01,ABS(M12)<=0.01),"OK","CHECK")
A13: 45170 | B13: 242 | C13: 527323.91 | D13: 515673.26 | E13: 11650.65 | F13: 842.65 | G13: 514830.61 | H13: 527323.91 | I13: 0 | J13: =ROUND(C13-D13-E13,2) | K13: =D13-F13 | L13: =ROUND(K13-G13,2) | M13: =ROUND(C13-H13-I13,2) | N13: =IF(AND(ABS(J13)<=0.01,ABS(L13)<=0.01,ABS(M13)<=0.01),"OK","CHECK")
A14: 45200 | B14: 267 | C14: 575330.68 | D14: 569455.38 | E14: 5875.3 | F14: 344.44 | G14: 569110.94 | H14: 575330.68 | I14: 0 | J14: =ROUND(C14-D14-E14,2) | K14: =D14-F14 | L14: =ROUND(K14-G14,2) | M14: =ROUND(C14-H14-I14,2) | N14: =IF(AND(ABS(J14)<=0.01,ABS(L14)<=0.01,ABS(M14)<=0.01),"OK","CHECK")
A15: 45231 | B15: 282 | C15: 602450.79 | D15: 594870.58 | E15: 7580.21 | F15: 526.61 | G15: 594343.97 | H15: 602450.79 | I15: 0 | J15: =ROUND(C15-D15-E15,2) | K15: =D15-F15 | L15: =ROUND(K15-G15,2) | M15: =ROUND(C15-H15-I15,2) | N15: =IF(AND(ABS(J15)<=0.01,ABS(L15)<=0.01,ABS(M15)<=0.01),"OK","CHECK")
A16: 45261 | B16: 307 | C16: 628549.58 | D16: 581311.68 | E16: 47237.9 | F16: 171.59 | G16: 581140.09 | H16: 628549.58 | I16: 0 | J16: =ROUND(C16-D16-E16,2) | K16: =D16-F16 | L16: =ROUND(K16-G16,2) | M16: =ROUND(C16-H16-I16,2) | N16: =IF(AND(ABS(J16)<=0.01,ABS(L16)<=0.01,ABS(M16)<=0.01),"OK","CHECK")
... A40: 45992 | B40: 888 | C40: 2259103 | D40: 2205381.1 | E40: 53721.83 | F40: 11112.32 | G40: 2194268.8 | H40: 2259103 | I40: 0 | J40: =ROUND(C40-D40-E40,2) | K40: =D40-F40 | L40: =ROUND(K40-G40,2) | M40: =ROUND(C40-H40-I40,2) | N40: =IF(AND(ABS(J40)<=0.01,ABS(L40)<=0.01,ABS(M40)<=0.01),"OK","CHECK")
A41: Total | B41: =SUM(B5:B40) | C41: =SUM(C5:C40) | D41: =SUM(D5:D40) | E41: =SUM(E5:E40) | F41: =SUM(F5:F40) | G41: =SUM(G5:G40) | H41: =SUM(H5:H40) | I41: =SUM(I5:I40) | ... M41: =SUM(M5:M40)

Sheet Exceptions
A1: Finance exception queue
A2: Summary formulas read the detail list below. Billed amount counts an invoice once per rule it breaks.
A4: Rule | B4: Severity | C4: Records | D4: Billed amount
A5: contract_date_conflict | B5: medium | C5: =COUNTIF($B$9:$B$977,A5) | D5: =SUMIF($B$9:$B$977,A5,$F$9:$F$977)
A6: Total | C6: =SUM(C5:C5) | D6: =SUM(D5:D5)
A8: Invoice | B8: Rule | C8: Severity | D8: Invoice date | E8: Customer | F8: Billed amount | G8: Details
A9: INV00001092 | B9: contract_date_conflict | C9: medium | D9: 44927 | E9: C000073 | F9: 1635.3 | G9: Invoice date falls outside the linked contract
A10: INV00001717 | B10: contract_date_conflict | C10: medium | D10: 44927 | E10: C000115 | F10: 386.1 | G10: Invoice date falls outside the linked contract
A11: INV00003367 | B11: contract_date_conflict | C11: medium | D11: 44927 | E11: C000245 | F11: 1501 | G11: Invoice date falls outside the linked contract
A12: INV00005443 | B12: contract_date_conflict | C12: medium | D12: 44927 | E12: C000390 | F12: 7360.6 | G12: Invoice date falls outside the linked contract
A13: INV00005545 | B13: contract_date_conflict | C13: medium | D13: 44927 | E13: C000395 | F13: 1350.9 | G13: Invoice date falls outside the linked contract
A14: INV00006648 | B14: contract_date_conflict | C14: medium | D14: 44927 | E14: C000475 | F14: 468 | G14: Invoice date falls outside the linked contract
A15: INV00007316 | B15: contract_date_conflict | C15: medium | D15: 44927 | E15: C000516 | F15: 1817 | G15: Invoice date falls outside the linked contract
A16: INV00007366 | B16: contract_date_conflict | C16: medium | D16: 44927 | E16: C000518 | F16: 1185 | G16: Invoice date falls outside the linked contract
A17: INV00007865 | B17: contract_date_conflict | C17: medium | D17: 44927 | E17: C000559 | F17: 2061.9 | G17: Invoice date falls outside the linked contract
A18: INV00008367 | B18: contract_date_conflict | C18: medium | D18: 44927 | E18: C000592 | F18: 10281 | G18: Invoice date falls outside the linked contract
A19: INV00008833 | B19: contract_date_conflict | C19: medium | D19: 44927 | E19: C000622 | F19: 1264 | G19: Invoice date falls outside the linked contract
A20: INV00009191 | B20: contract_date_conflict | C20: medium | D20: 44927 | E20: C000642 | F20: 948 | G20: Invoice date falls outside the linked contract
... A977: INV00017348 | B977: contract_date_conflict | C977: medium | D977: 45992 | E977: C001200 | F977: 3634 | G977: Invoice date falls outside the linked contract

Sheet Scenario Inputs
A1: Scenario inputs
A2: Shaded cells are the only editable cells in this workbook. Outputs are simulated, not observed.
A4: Assumption | B4: Value | C4: Meaning
A5: Churn reduction | B5: 0.1 | C5: Share of churned MRR avoided each month
A6: Pricing change | B6: 0.03 | C6: Uplift applied to closing MRR
A7: Expansion uplift | B7: 0.1 | C7: Extra expansion as a share of observed expansion MRR
A8: Failed-payment recovery | B8: 0.2 | C8: Share of unpaid failed exposure recovered as cash

Sheet Scenario Output
A1: Scenario output (simulated)
A2: Formulas apply the shaded assumptions to observed monthly values. Not a forecast.
A4: Month | B4: Baseline MRR | C4: Avoided churn | D4: Extra expansion | E4: Pricing effect | F4: Scenario MRR | G4: Incremental MRR | H4: Baseline net cash | I4: Recovered cash | J4: Scenario net cash
A5: ='MRR Bridge'!A5 | B5: ='MRR Bridge'!H5 | C5: ='MRR Bridge'!G5*'Scenario Inputs'!$B$5 | D5: ='MRR Bridge'!D5*'Scenario Inputs'!$B$7 | E5: ='MRR Bridge'!H5*'Scenario Inputs'!$B$6 | F5: =B5+C5+D5+E5 | G5: =F5-B5 | H5: ='Billing Reconciliation'!G5 | I5: ='Billing Reconciliation'!E5*'Scenario Inputs'!$B$8 | J5: =H5+I5
A6: ='MRR Bridge'!A6 | B6: ='MRR Bridge'!H6 | C6: ='MRR Bridge'!G6*'Scenario Inputs'!$B$5 | D6: ='MRR Bridge'!D6*'Scenario Inputs'!$B$7 | E6: ='MRR Bridge'!H6*'Scenario Inputs'!$B$6 | F6: =B6+C6+D6+E6 | G6: =F6-B6 | H6: ='Billing Reconciliation'!G6 | I6: ='Billing Reconciliation'!E6*'Scenario Inputs'!$B$8 | J6: =H6+I6
A7: ='MRR Bridge'!A7 | B7: ='MRR Bridge'!H7 | C7: ='MRR Bridge'!G7*'Scenario Inputs'!$B$5 | D7: ='MRR Bridge'!D7*'Scenario Inputs'!$B$7 | E7: ='MRR Bridge'!H7*'Scenario Inputs'!$B$6 | F7: =B7+C7+D7+E7 | G7: =F7-B7 | H7: ='Billing Reconciliation'!G7 | I7: ='Billing Reconciliation'!E7*'Scenario Inputs'!$B$8 | J7: =H7+I7
A8: ='MRR Bridge'!A8 | B8: ='MRR Bridge'!H8 | C8: ='MRR Bridge'!G8*'Scenario Inputs'!$B$5 | D8: ='MRR Bridge'!D8*'Scenario Inputs'!$B$7 | E8: ='MRR Bridge'!H8*'Scenario Inputs'!$B$6 | F8: =B8+C8+D8+E8 | G8: =F8-B8 | H8: ='Billing Reconciliation'!G8 | I8: ='Billing Reconciliation'!E8*'Scenario Inputs'!$B$8 | J8: =H8+I8
A9: ='MRR Bridge'!A9 | B9: ='MRR Bridge'!H9 | C9: ='MRR Bridge'!G9*'Scenario Inputs'!$B$5 | D9: ='MRR Bridge'!D9*'Scenario Inputs'!$B$7 | E9: ='MRR Bridge'!H9*'Scenario Inputs'!$B$6 | F9: =B9+C9+D9+E9 | G9: =F9-B9 | H9: ='Billing Reconciliation'!G9 | I9: ='Billing Reconciliation'!E9*'Scenario Inputs'!$B$8 | J9: =H9+I9
A10: ='MRR Bridge'!A10 | B10: ='MRR Bridge'!H10 | C10: ='MRR Bridge'!G10*'Scenario Inputs'!$B$5 | D10: ='MRR Bridge'!D10*'Scenario Inputs'!$B$7 | E10: ='MRR Bridge'!H10*'Scenario Inputs'!$B$6 | F10: =B10+C10+D10+E10 | G10: =F10-B10 | H10: ='Billing Reconciliation'!G10 | I10: ='Billing Reconciliation'!E10*'Scenario Inputs'!$B$8 | J10: =H10+I10
A11: ='MRR Bridge'!A11 | B11: ='MRR Bridge'!H11 | C11: ='MRR Bridge'!G11*'Scenario Inputs'!$B$5 | D11: ='MRR Bridge'!D11*'Scenario Inputs'!$B$7 | E11: ='MRR Bridge'!H11*'Scenario Inputs'!$B$6 | F11: =B11+C11+D11+E11 | G11: =F11-B11 | H11: ='Billing Reconciliation'!G11 | I11: ='Billing Reconciliation'!E11*'Scenario Inputs'!$B$8 | J11: =H11+I11
A12: ='MRR Bridge'!A12 | B12: ='MRR Bridge'!H12 | C12: ='MRR Bridge'!G12*'Scenario Inputs'!$B$5 | D12: ='MRR Bridge'!D12*'Scenario Inputs'!$B$7 | E12: ='MRR Bridge'!H12*'Scenario Inputs'!$B$6 | F12: =B12+C12+D12+E12 | G12: =F12-B12 | H12: ='Billing Reconciliation'!G12 | I12: ='Billing Reconciliation'!E12*'Scenario Inputs'!$B$8 | J12: =H12+I12
A13: ='MRR Bridge'!A13 | B13: ='MRR Bridge'!H13 | C13: ='MRR Bridge'!G13*'Scenario Inputs'!$B$5 | D13: ='MRR Bridge'!D13*'Scenario Inputs'!$B$7 | E13: ='MRR Bridge'!H13*'Scenario Inputs'!$B$6 | F13: =B13+C13+D13+E13 | G13: =F13-B13 | H13: ='Billing Reconciliation'!G13 | I13: ='Billing Reconciliation'!E13*'Scenario Inputs'!$B$8 | J13: =H13+I13
A14: ='MRR Bridge'!A14 | B14: ='MRR Bridge'!H14 | C14: ='MRR Bridge'!G14*'Scenario Inputs'!$B$5 | D14: ='MRR Bridge'!D14*'Scenario Inputs'!$B$7 | E14: ='MRR Bridge'!H14*'Scenario Inputs'!$B$6 | F14: =B14+C14+D14+E14 | G14: =F14-B14 | H14: ='Billing Reconciliation'!G14 | I14: ='Billing Reconciliation'!E14*'Scenario Inputs'!$B$8 | J14: =H14+I14
A15: ='MRR Bridge'!A15 | B15: ='MRR Bridge'!H15 | C15: ='MRR Bridge'!G15*'Scenario Inputs'!$B$5 | D15: ='MRR Bridge'!D15*'Scenario Inputs'!$B$7 | E15: ='MRR Bridge'!H15*'Scenario Inputs'!$B$6 | F15: =B15+C15+D15+E15 | G15: =F15-B15 | H15: ='Billing Reconciliation'!G15 | I15: ='Billing Reconciliation'!E15*'Scenario Inputs'!$B$8 | J15: =H15+I15
A16: ='MRR Bridge'!A16 | B16: ='MRR Bridge'!H16 | C16: ='MRR Bridge'!G16*'Scenario Inputs'!$B$5 | D16: ='MRR Bridge'!D16*'Scenario Inputs'!$B$7 | E16: ='MRR Bridge'!H16*'Scenario Inputs'!$B$6 | F16: =B16+C16+D16+E16 | G16: =F16-B16 | H16: ='Billing Reconciliation'!G16 | I16: ='Billing Reconciliation'!E16*'Scenario Inputs'!$B$8 | J16: =H16+I16
... A40: ='MRR Bridge'!A40 | B40: ='MRR Bridge'!H40 | C40: ='MRR Bridge'!G40*'Scenario Inputs'!$B$5 | D40: ='MRR Bridge'!D40*'Scenario Inputs'!$B$7 | E40: ='MRR Bridge'!H40*'Scenario Inputs'!$B$6 | F40: =B40+C40+D40+E40 | G40: =F40-B40 | H40: ='Billing Reconciliation'!G40 | I40: ='Billing Reconciliation'!E40*'Scenario Inputs'!$B$8 | J40: =H40+I40

Sheet Metric Definitions
A1: Metric definitions (implemented metrics only)
A3: Metric | B3: Definition | C3: Where in this workbook | D3: Source mart
A4: MRR | B4: Sum of active subscription monthly recurring revenue at month end | C4: Closing MRR | D4: mart_mrr_bridge
A5: Net new MRR | B5: New + expansion + reactivation - contraction - churned | C5: C+D+E-F-G | D5: mart_mrr_bridge
A6: NRR | B6: (Opening + expansion + reactivation - contraction - churned) / opening | C6: MRR Bridge column M | D6: mart_revenue_kpis
A7: GRR | B7: (Opening - contraction - churned) / opening | C7: MRR Bridge column N | D7: mart_revenue_kpis
A8: Tie-out variance | B8: Invoiced - successful payments - unpaid failed exposure | C8: Billing Reconciliation column J | D8: fct_billing_reconciliation
A9: Net cash | B9: Successful payments - refunds | C9: Billing Reconciliation column K | D9: fct_billing_reconciliation
A10: Failed-payment exposure | B10: Invoice total on invoices without a successful payment | C10: Billing Reconciliation column E | D10: fct_billing_reconciliation
A11: Finance exception | B11: Invoice-level rule violation queued for review | C11: Exceptions sheet | D11: mart_finance_exceptions
